{
  "date" : "Mon, 30 Sep, 2024 11:49:20 +0000",
  "doco" : "For each file: start is seconds after start activity occurred. Length = milliseconds activity took",
  "files" : [
    {
      "name" : "/fsh-generated/resources/ImplementationGuide-ans.fhir.fr.sdo.json",
      "size" : 10700,
      "processes" : [
        {
          "activity" : "load-configure",
          "start" : 30,
          "length" : 1
        },
        {
          "activity" : "scan",
          "start" : 30,
          "length" : 1
        },
        {
          "activity" : "load",
          "start" : 30,
          "length" : 12
        },
        {
          "activity" : "checkR4R4B",
          "start" : 31,
          "length" : 5
        },
        {
          "activity" : "generateNarratives",
          "start" : 31,
          "length" : 74
        },
        {
          "activity" : "validate",
          "start" : 36,
          "length" : 3741
        },
        {
          "activity" : "scanForUsageStats",
          "start" : 40,
          "length" : 2
        },
        {
          "activity" : "generate1",
          "start" : 41,
          "length" : 110
        },
        {
          "activity" : "generate2",
          "start" : 45,
          "length" : 126
        },
        {
          "activity" : "generateValidationPack",
          "start" : 64,
          "length" : 4
        },
        {
          "activity" : "scanExamplesForR5",
          "start" : 73,
          "length" : 1
        }
      ]
    },
    {
      "name" : "fsh-generated/resources/Bundle-exemple-bundle-resultat-recherche-decision-evaluation-elements.json",
      "size" : 2535,
      "processes" : [
        {
          "activity" : "loadResources",
          "start" : 29,
          "length" : 13
        },
        {
          "activity" : "loadInfo",
          "start" : 30,
          "length" : 1
        },
        {
          "activity" : "load",
          "start" : 30,
          "length" : 20
        },
        {
          "activity" : "load",
          "start" : 30,
          "length" : 1
        },
        {
          "activity" : "generateNarratives",
          "start" : 31,
          "length" : 16
        },
        {
          "activity" : "validate",
          "start" : 40,
          "length" : 120
        },
        {
          "activity" : "generate1",
          "start" : 41,
          "length" : 50
        },
        {
          "activity" : "generate2",
          "start" : 45,
          "length" : 42
        }
      ]
    },
    {
      "name" : "fsh-generated/resources/Bundle-exemple-bundle-resultat-recherche-decision-evaluation.json",
      "size" : 2724,
      "processes" : [
        {
          "activity" : "loadResources",
          "start" : 29,
          "length" : 12
        },
        {
          "activity" : "load",
          "start" : 30,
          "length" : 8
        },
        {
          "activity" : "generateNarratives",
          "start" : 31,
          "length" : 169
        },
        {
          "activity" : "validate",
          "start" : 40,
          "length" : 109
        },
        {
          "activity" : "generate1",
          "start" : 41,
          "length" : 43
        },
        {
          "activity" : "generate2",
          "start" : 45,
          "length" : 38
        }
      ]
    },
    {
      "name" : "fsh-generated/resources/Bundle-exemple-sdo-bundle-resultat-recherche-notifications-esms.json",
      "size" : 12319,
      "processes" : [
        {
          "activity" : "loadResources",
          "start" : 29,
          "length" : 14
        },
        {
          "activity" : "load",
          "start" : 30,
          "length" : 13
        },
        {
          "activity" : "checkR4R4B",
          "start" : 31,
          "length" : 1
        },
        {
          "activity" : "generateNarratives",
          "start" : 31,
          "length" : 54
        },
        {
          "activity" : "validate",
          "start" : 40,
          "length" : 209
        },
        {
          "activity" : "generate1",
          "start" : 41,
          "length" : 57
        },
        {
          "activity" : "generate2",
          "start" : 45,
          "length" : 50
        }
      ]
    },
    {
      "name" : "fsh-generated/resources/CapabilityStatement-ESMSConsommateur.json",
      "size" : 2507,
      "processes" : [
        {
          "activity" : "loadResources",
          "start" : 29,
          "length" : 12
        },
        {
          "activity" : "loadDepInfo",
          "start" : 30,
          "length" : 1
        },
        {
          "activity" : "load",
          "start" : 30,
          "length" : 24
        },
        {
          "activity" : "generateNarratives",
          "start" : 31,
          "length" : 47
        },
        {
          "activity" : "validate",
          "start" : 36,
          "length" : 181
        },
        {
          "activity" : "generate1",
          "start" : 41,
          "length" : 56
        },
        {
          "activity" : "generate2",
          "start" : 46,
          "length" : 82
        },
        {
          "activity" : "makeDependencies",
          "start" : 57,
          "length" : 1
        },
        {
          "activity" : "generateValidationPack",
          "start" : 64,
          "length" : 1
        }
      ]
    },
    {
      "name" : "fsh-generated/resources/CapabilityStatement-ESMSProducteur.json",
      "size" : 1912,
      "processes" : [
        {
          "activity" : "loadResources",
          "start" : 29,
          "length" : 11
        },
        {
          "activity" : "load",
          "start" : 30,
          "length" : 3
        },
        {
          "activity" : "generateNarratives",
          "start" : 31,
          "length" : 18
        },
        {
          "activity" : "validate",
          "start" : 36,
          "length" : 88
        },
        {
          "activity" : "generate1",
          "start" : 41,
          "length" : 47
        },
        {
          "activity" : "generate2",
          "start" : 46,
          "length" : 59
        },
        {
          "activity" : "generateValidationPack",
          "start" : 64,
          "length" : 1
        }
      ]
    },
    {
      "name" : "fsh-generated/resources/CapabilityStatement-gestionnaire-sdo.json",
      "size" : 2756,
      "processes" : [
        {
          "activity" : "loadResources",
          "start" : 29,
          "length" : 10
        },
        {
          "activity" : "load",
          "start" : 30,
          "length" : 4
        },
        {
          "activity" : "generateNarratives",
          "start" : 31,
          "length" : 24
        },
        {
          "activity" : "validate",
          "start" : 36,
          "length" : 10
        },
        {
          "activity" : "generate1",
          "start" : 41,
          "length" : 42
        },
        {
          "activity" : "generate2",
          "start" : 46,
          "length" : 71
        },
        {
          "activity" : "generateValidationPack",
          "start" : 64,
          "length" : 1
        }
      ]
    },
    {
      "name" : "fsh-generated/resources/CodeSystem-input-task-sdo-codesystem.json",
      "size" : 4297,
      "processes" : [
        {
          "activity" : "loadResources",
          "start" : 29,
          "length" : 11
        },
        {
          "activity" : "load-configure",
          "start" : 30,
          "length" : 1
        },
        {
          "activity" : "load",
          "start" : 30,
          "length" : 25
        },
        {
          "activity" : "checkR4R4B",
          "start" : 31,
          "length" : 1
        },
        {
          "activity" : "generateNarratives",
          "start" : 31,
          "length" : 25
        },
        {
          "activity" : "validate",
          "start" : 32,
          "length" : 455
        },
        {
          "activity" : "generate1",
          "start" : 41,
          "length" : 44
        },
        {
          "activity" : "generate2",
          "start" : 46,
          "length" : 1753
        },
        {
          "activity" : "generateValidationPack",
          "start" : 64,
          "length" : 1
        }
      ]
    },
    {
      "name" : "fsh-generated/resources/Consent-exemple-consent.json",
      "size" : 1058,
      "processes" : [
        {
          "activity" : "loadResources",
          "start" : 29,
          "length" : 11
        },
        {
          "activity" : "generateNarratives",
          "start" : 31,
          "length" : 242
        },
        {
          "activity" : "validate",
          "start" : 40,
          "length" : 167
        },
        {
          "activity" : "generate1",
          "start" : 41,
          "length" : 30
        },
        {
          "activity" : "generate2",
          "start" : 48,
          "length" : 47
        }
      ]
    },
    {
      "name" : "fsh-generated/resources/DocumentReference-exemple-esms-document-reference.json",
      "size" : 756,
      "processes" : [
        {
          "activity" : "loadResources",
          "start" : 29,
          "length" : 10
        },
        {
          "activity" : "generateNarratives",
          "start" : 31,
          "length" : 1
        },
        {
          "activity" : "validate",
          "start" : 40,
          "length" : 83
        },
        {
          "activity" : "generate1",
          "start" : 41,
          "length" : 24
        },
        {
          "activity" : "generate2",
          "start" : 48,
          "length" : 27
        }
      ]
    },
    {
      "name" : "fsh-generated/resources/DocumentReference-exemple-sdo-document-reference.json",
      "size" : 545,
      "processes" : [
        {
          "activity" : "loadResources",
          "start" : 29,
          "length" : 10
        },
        {
          "activity" : "generateNarratives",
          "start" : 31,
          "length" : 2
        },
        {
          "activity" : "validate",
          "start" : 40,
          "length" : 4
        },
        {
          "activity" : "generate1",
          "start" : 41,
          "length" : 24
        },
        {
          "activity" : "generate2",
          "start" : 48,
          "length" : 37
        }
      ]
    },
    {
      "name" : "fsh-generated/resources/StructureDefinition-esms-bundle-resultat-recherche-decision-evaluation.json",
      "size" : 1288,
      "processes" : [
        {
          "activity" : "loadResources",
          "start" : 29,
          "length" : 11
        },
        {
          "activity" : "load",
          "start" : 30,
          "length" : 18
        },
        {
          "activity" : "generateSnapshots",
          "start" : 30,
          "length" : 104
        },
        {
          "activity" : "generateNarratives",
          "start" : 31,
          "length" : 54
        },
        {
          "activity" : "validate",
          "start" : 32,
          "length" : 494
        },
        {
          "activity" : "generate1",
          "start" : 41,
          "length" : 160
        },
        {
          "activity" : "generate2",
          "start" : 48,
          "length" : 1262
        },
        {
          "activity" : "generateValidationPack",
          "start" : 64,
          "length" : 6
        },
        {
          "activity" : "scanExamplesForR5",
          "start" : 73,
          "length" : 1
        }
      ]
    },
    {
      "name" : "fsh-generated/resources/StructureDefinition-esms-consent.json",
      "size" : 3278,
      "processes" : [
        {
          "activity" : "loadResources",
          "start" : 29,
          "length" : 12
        },
        {
          "activity" : "load",
          "start" : 30,
          "length" : 21
        },
        {
          "activity" : "generateSnapshots",
          "start" : 30,
          "length" : 80
        },
        {
          "activity" : "generateNarratives",
          "start" : 31,
          "length" : 51
        },
        {
          "activity" : "validate",
          "start" : 33,
          "length" : 532
        },
        {
          "activity" : "checkConformanceResources",
          "start" : 40,
          "length" : 1
        },
        {
          "activity" : "scanForUsageStats",
          "start" : 40,
          "length" : 1
        },
        {
          "activity" : "generate1",
          "start" : 41,
          "length" : 235
        },
        {
          "activity" : "generate2",
          "start" : 49,
          "length" : 991
        },
        {
          "activity" : "generateValidationPack",
          "start" : 64,
          "length" : 13
        },
        {
          "activity" : "scanExamplesForR5",
          "start" : 73,
          "length" : 2
        }
      ]
    },
    {
      "name" : "fsh-generated/resources/StructureDefinition-esms-document-reference.json",
      "size" : 2355,
      "processes" : [
        {
          "activity" : "loadResources",
          "start" : 29,
          "length" : 10
        },
        {
          "activity" : "load",
          "start" : 30,
          "length" : 19
        },
        {
          "activity" : "generateSnapshots",
          "start" : 30,
          "length" : 84
        },
        {
          "activity" : "generateNarratives",
          "start" : 31,
          "length" : 48
        },
        {
          "activity" : "validate",
          "start" : 33,
          "length" : 453
        },
        {
          "activity" : "scanForUsageStats",
          "start" : 40,
          "length" : 1
        },
        {
          "activity" : "generate1",
          "start" : 42,
          "length" : 231
        },
        {
          "activity" : "generate2",
          "start" : 50,
          "length" : 797
        },
        {
          "activity" : "generateValidationPack",
          "start" : 64,
          "length" : 13
        }
      ]
    },
    {
      "name" : "fsh-generated/resources/StructureDefinition-sdo-bundle-resultat-recherche-notification-esms.json",
      "size" : 1082,
      "processes" : [
        {
          "activity" : "loadResources",
          "start" : 29,
          "length" : 10
        },
        {
          "activity" : "load",
          "start" : 30,
          "length" : 18
        },
        {
          "activity" : "generateSnapshots",
          "start" : 30,
          "length" : 132
        },
        {
          "activity" : "generateNarratives",
          "start" : 32,
          "length" : 31
        },
        {
          "activity" : "validate",
          "start" : 34,
          "length" : 223
        },
        {
          "activity" : "generateLogicalMaps",
          "start" : 40,
          "length" : 1
        },
        {
          "activity" : "scanForUsageStats",
          "start" : 40,
          "length" : 3
        },
        {
          "activity" : "generate1",
          "start" : 42,
          "length" : 158
        },
        {
          "activity" : "generate2",
          "start" : 51,
          "length" : 485
        },
        {
          "activity" : "generateValidationPack",
          "start" : 64,
          "length" : 6
        },
        {
          "activity" : "scanProfilesForR5",
          "start" : 73,
          "length" : 1
        },
        {
          "activity" : "scanExamplesForR5",
          "start" : 73,
          "length" : 1
        }
      ]
    },
    {
      "name" : "fsh-generated/resources/StructureDefinition-sdo-document-reference.json",
      "size" : 3116,
      "processes" : [
        {
          "activity" : "loadResources",
          "start" : 29,
          "length" : 11
        },
        {
          "activity" : "load",
          "start" : 30,
          "length" : 19
        },
        {
          "activity" : "generateNarratives",
          "start" : 32,
          "length" : 77
        },
        {
          "activity" : "validate",
          "start" : 34,
          "length" : 529
        },
        {
          "activity" : "scanForUsageStats",
          "start" : 40,
          "length" : 1
        },
        {
          "activity" : "generate1",
          "start" : 42,
          "length" : 252
        },
        {
          "activity" : "generate2",
          "start" : 51,
          "length" : 641
        },
        {
          "activity" : "generateValidationPack",
          "start" : 64,
          "length" : 12
        }
      ]
    },
    {
      "name" : "fsh-generated/resources/StructureDefinition-sdo-task.json",
      "size" : 18814,
      "processes" : [
        {
          "activity" : "loadResources",
          "start" : 29,
          "length" : 14
        },
        {
          "activity" : "load-configure",
          "start" : 30,
          "length" : 1
        },
        {
          "activity" : "load",
          "start" : 30,
          "length" : 33
        },
        {
          "activity" : "generateSnapshots",
          "start" : 31,
          "length" : 83
        },
        {
          "activity" : "generateNarratives",
          "start" : 32,
          "length" : 131
        },
        {
          "activity" : "validate",
          "start" : 35,
          "length" : 1019
        },
        {
          "activity" : "scanForUsageStats",
          "start" : 40,
          "length" : 3
        },
        {
          "activity" : "generate1",
          "start" : 42,
          "length" : 626
        },
        {
          "activity" : "generate2",
          "start" : 52,
          "length" : 1406
        },
        {
          "activity" : "generateValidationPack",
          "start" : 64,
          "length" : 35
        },
        {
          "activity" : "scanExamplesForR5",
          "start" : 73,
          "length" : 2
        }
      ]
    },
    {
      "name" : "fsh-generated/resources/Task-exemple-sdo-task.json",
      "size" : 6501,
      "processes" : [
        {
          "activity" : "loadResources",
          "start" : 29,
          "length" : 11
        },
        {
          "activity" : "checkR4R4B",
          "start" : 31,
          "length" : 1
        },
        {
          "activity" : "generateNarratives",
          "start" : 32,
          "length" : 6
        },
        {
          "activity" : "validate",
          "start" : 40,
          "length" : 46
        },
        {
          "activity" : "generate1",
          "start" : 43,
          "length" : 33
        },
        {
          "activity" : "generate2",
          "start" : 53,
          "length" : 41
        }
      ]
    },
    {
      "name" : "fsh-generated/resources/ValueSet-type-document-reference-esms-valueset.json",
      "size" : 781,
      "processes" : [
        {
          "activity" : "loadResources",
          "start" : 29,
          "length" : 13
        },
        {
          "activity" : "load",
          "start" : 30,
          "length" : 19
        },
        {
          "activity" : "generateNarratives",
          "start" : 32,
          "length" : 130
        },
        {
          "activity" : "validate",
          "start" : 32,
          "length" : 94
        },
        {
          "activity" : "generate1",
          "start" : 43,
          "length" : 26
        },
        {
          "activity" : "generate2",
          "start" : 53,
          "length" : 1567
        }
      ]
    }
  ]
}
