{
  "date" : "Tue, 26 Nov, 2024 07:49:21 +0000",
  "doco" : "For each file: start is seconds after start activity occurred. Length = milliseconds activity took",
  "files" : [
    {
      "name" : "/fsh-generated/resources/ImplementationGuide-ans.fhir.fr.sdo.json",
      "size" : 11116,
      "processes" : [
        {
          "activity" : "load",
          "start" : 32,
          "length" : 15
        },
        {
          "activity" : "checkR4R4B",
          "start" : 33,
          "length" : 10
        },
        {
          "activity" : "generateNarratives",
          "start" : 33,
          "length" : 182
        },
        {
          "activity" : "validate",
          "start" : 40,
          "length" : 4166
        },
        {
          "activity" : "generate1",
          "start" : 45,
          "length" : 132
        },
        {
          "activity" : "generate2",
          "start" : 51,
          "length" : 111
        },
        {
          "activity" : "generateValidationPack",
          "start" : 70,
          "length" : 4
        },
        {
          "activity" : "scanExamplesForR5",
          "start" : 79,
          "length" : 1
        }
      ]
    },
    {
      "name" : "fsh-generated/resources/Bundle-exemple-bundle-resultat-recherche-decision-evaluation-elements.json",
      "size" : 2535,
      "processes" : [
        {
          "activity" : "loadResources",
          "start" : 31,
          "length" : 22
        },
        {
          "activity" : "load",
          "start" : 32,
          "length" : 8
        },
        {
          "activity" : "checkR4R4B",
          "start" : 33,
          "length" : 1
        },
        {
          "activity" : "generateNarratives",
          "start" : 33,
          "length" : 14
        },
        {
          "activity" : "validate",
          "start" : 44,
          "length" : 127
        },
        {
          "activity" : "generate1",
          "start" : 45,
          "length" : 31
        },
        {
          "activity" : "generate2",
          "start" : 51,
          "length" : 20
        }
      ]
    },
    {
      "name" : "fsh-generated/resources/Bundle-exemple-bundle-resultat-recherche-decision-evaluation.json",
      "size" : 2724,
      "processes" : [
        {
          "activity" : "loadResources",
          "start" : 31,
          "length" : 20
        },
        {
          "activity" : "load",
          "start" : 32,
          "length" : 4
        },
        {
          "activity" : "generateNarratives",
          "start" : 33,
          "length" : 166
        },
        {
          "activity" : "validate",
          "start" : 44,
          "length" : 121
        },
        {
          "activity" : "generate1",
          "start" : 45,
          "length" : 29
        },
        {
          "activity" : "generate2",
          "start" : 51,
          "length" : 19
        }
      ]
    },
    {
      "name" : "fsh-generated/resources/Bundle-exemple-sdo-bundle-resultat-recherche-notifications-esms.json",
      "size" : 12319,
      "processes" : [
        {
          "activity" : "loadResources",
          "start" : 31,
          "length" : 23
        },
        {
          "activity" : "load",
          "start" : 32,
          "length" : 10
        },
        {
          "activity" : "checkR4R4B",
          "start" : 33,
          "length" : 1
        },
        {
          "activity" : "generateNarratives",
          "start" : 33,
          "length" : 49
        },
        {
          "activity" : "scanForUsageStats",
          "start" : 44,
          "length" : 1
        },
        {
          "activity" : "validate",
          "start" : 45,
          "length" : 184
        },
        {
          "activity" : "generate1",
          "start" : 45,
          "length" : 68
        },
        {
          "activity" : "generate2",
          "start" : 51,
          "length" : 35
        }
      ]
    },
    {
      "name" : "fsh-generated/resources/CapabilityStatement-ESMSConsommateur.json",
      "size" : 2507,
      "processes" : [
        {
          "activity" : "loadResources",
          "start" : 31,
          "length" : 19
        },
        {
          "activity" : "loadDepInfo",
          "start" : 32,
          "length" : 1
        },
        {
          "activity" : "load",
          "start" : 32,
          "length" : 10
        },
        {
          "activity" : "generateNarratives",
          "start" : 33,
          "length" : 47
        },
        {
          "activity" : "validate",
          "start" : 40,
          "length" : 218
        },
        {
          "activity" : "generate1",
          "start" : 45,
          "length" : 41
        },
        {
          "activity" : "generate2",
          "start" : 51,
          "length" : 45
        },
        {
          "activity" : "generateValidationPack",
          "start" : 70,
          "length" : 1
        }
      ]
    },
    {
      "name" : "fsh-generated/resources/CapabilityStatement-ESMSProducteur.json",
      "size" : 1912,
      "processes" : [
        {
          "activity" : "loadResources",
          "start" : 31,
          "length" : 19
        },
        {
          "activity" : "load",
          "start" : 32,
          "length" : 5
        },
        {
          "activity" : "generateNarratives",
          "start" : 33,
          "length" : 26
        },
        {
          "activity" : "validate",
          "start" : 40,
          "length" : 110
        },
        {
          "activity" : "generate1",
          "start" : 45,
          "length" : 31
        },
        {
          "activity" : "generate2",
          "start" : 51,
          "length" : 25
        },
        {
          "activity" : "generateValidationPack",
          "start" : 70,
          "length" : 1
        }
      ]
    },
    {
      "name" : "fsh-generated/resources/CapabilityStatement-gestionnaire-sdo.json",
      "size" : 2756,
      "processes" : [
        {
          "activity" : "loadResources",
          "start" : 31,
          "length" : 19
        },
        {
          "activity" : "load-configure",
          "start" : 32,
          "length" : 1
        },
        {
          "activity" : "load",
          "start" : 32,
          "length" : 6
        },
        {
          "activity" : "generateNarratives",
          "start" : 33,
          "length" : 26
        },
        {
          "activity" : "validate",
          "start" : 40,
          "length" : 5
        },
        {
          "activity" : "generate1",
          "start" : 46,
          "length" : 36
        },
        {
          "activity" : "generate2",
          "start" : 51,
          "length" : 35
        },
        {
          "activity" : "generateValidationPack",
          "start" : 70,
          "length" : 1
        }
      ]
    },
    {
      "name" : "fsh-generated/resources/CodeSystem-input-task-sdo-codesystem.json",
      "size" : 4297,
      "processes" : [
        {
          "activity" : "loadResources",
          "start" : 31,
          "length" : 20
        },
        {
          "activity" : "load",
          "start" : 32,
          "length" : 11
        },
        {
          "activity" : "checkR4R4B",
          "start" : 33,
          "length" : 1
        },
        {
          "activity" : "generateNarratives",
          "start" : 33,
          "length" : 28
        },
        {
          "activity" : "validate",
          "start" : 34,
          "length" : 614
        },
        {
          "activity" : "generate1",
          "start" : 46,
          "length" : 31
        },
        {
          "activity" : "generate2",
          "start" : 51,
          "length" : 2565
        },
        {
          "activity" : "generateValidationPack",
          "start" : 70,
          "length" : 1
        }
      ]
    },
    {
      "name" : "fsh-generated/resources/Consent-exemple-consent.json",
      "size" : 1058,
      "processes" : [
        {
          "activity" : "loadResources",
          "start" : 31,
          "length" : 19
        },
        {
          "activity" : "generateNarratives",
          "start" : 33,
          "length" : 248
        },
        {
          "activity" : "validate",
          "start" : 45,
          "length" : 195
        },
        {
          "activity" : "generate1",
          "start" : 46,
          "length" : 18
        },
        {
          "activity" : "generate2",
          "start" : 54,
          "length" : 23
        }
      ]
    },
    {
      "name" : "fsh-generated/resources/DocumentReference-exemple-esms-document-reference.json",
      "size" : 756,
      "processes" : [
        {
          "activity" : "loadResources",
          "start" : 31,
          "length" : 18
        },
        {
          "activity" : "generateNarratives",
          "start" : 33,
          "length" : 2
        },
        {
          "activity" : "validate",
          "start" : 45,
          "length" : 106
        },
        {
          "activity" : "generate1",
          "start" : 46,
          "length" : 108
        },
        {
          "activity" : "generate2",
          "start" : 54,
          "length" : 10
        }
      ]
    },
    {
      "name" : "fsh-generated/resources/DocumentReference-exemple-sdo-document-reference.json",
      "size" : 545,
      "processes" : [
        {
          "activity" : "loadResources",
          "start" : 31,
          "length" : 11
        },
        {
          "activity" : "generateNarratives",
          "start" : 33,
          "length" : 2
        },
        {
          "activity" : "validate",
          "start" : 45,
          "length" : 3
        },
        {
          "activity" : "generate1",
          "start" : 46,
          "length" : 9
        },
        {
          "activity" : "generate2",
          "start" : 54,
          "length" : 9
        }
      ]
    },
    {
      "name" : "fsh-generated/resources/StructureDefinition-esms-bundle-resultat-recherche-decision-evaluation.json",
      "size" : 1320,
      "processes" : [
        {
          "activity" : "loadResources",
          "start" : 31,
          "length" : 11
        },
        {
          "activity" : "scan",
          "start" : 32,
          "length" : 1
        },
        {
          "activity" : "load",
          "start" : 32,
          "length" : 4
        },
        {
          "activity" : "generateSnapshots",
          "start" : 32,
          "length" : 109
        },
        {
          "activity" : "generateNarratives",
          "start" : 33,
          "length" : 54
        },
        {
          "activity" : "validate",
          "start" : 35,
          "length" : 713
        },
        {
          "activity" : "checkConformanceResources",
          "start" : 44,
          "length" : 1
        },
        {
          "activity" : "scanForUsageStats",
          "start" : 44,
          "length" : 1
        },
        {
          "activity" : "generate1",
          "start" : 46,
          "length" : 258
        },
        {
          "activity" : "generate2",
          "start" : 54,
          "length" : 1243
        },
        {
          "activity" : "generateValidationPack",
          "start" : 70,
          "length" : 6
        },
        {
          "activity" : "scanExamplesForR5",
          "start" : 79,
          "length" : 1
        }
      ]
    },
    {
      "name" : "fsh-generated/resources/StructureDefinition-esms-consent.json",
      "size" : 3343,
      "processes" : [
        {
          "activity" : "loadResources",
          "start" : 31,
          "length" : 12
        },
        {
          "activity" : "load",
          "start" : 32,
          "length" : 4
        },
        {
          "activity" : "generateSnapshots",
          "start" : 32,
          "length" : 69
        },
        {
          "activity" : "generateNarratives",
          "start" : 33,
          "length" : 57
        },
        {
          "activity" : "validate",
          "start" : 35,
          "length" : 1019
        },
        {
          "activity" : "scanForUsageStats",
          "start" : 44,
          "length" : 1
        },
        {
          "activity" : "generate1",
          "start" : 46,
          "length" : 473
        },
        {
          "activity" : "generate2",
          "start" : 55,
          "length" : 1098
        },
        {
          "activity" : "generateExampleZip",
          "start" : 69,
          "length" : 1
        },
        {
          "activity" : "generateValidationPack",
          "start" : 70,
          "length" : 13
        },
        {
          "activity" : "scanExamplesForR5",
          "start" : 79,
          "length" : 2
        }
      ]
    },
    {
      "name" : "fsh-generated/resources/StructureDefinition-esms-document-reference.json",
      "size" : 2500,
      "processes" : [
        {
          "activity" : "loadResources",
          "start" : 31,
          "length" : 11
        },
        {
          "activity" : "load",
          "start" : 32,
          "length" : 4
        },
        {
          "activity" : "generateSnapshots",
          "start" : 32,
          "length" : 96
        },
        {
          "activity" : "generateNarratives",
          "start" : 33,
          "length" : 52
        },
        {
          "activity" : "validate",
          "start" : 36,
          "length" : 858
        },
        {
          "activity" : "scanForUsageStats",
          "start" : 44,
          "length" : 2
        },
        {
          "activity" : "generate1",
          "start" : 46,
          "length" : 417
        },
        {
          "activity" : "generate2",
          "start" : 56,
          "length" : 934
        },
        {
          "activity" : "generateValidationPack",
          "start" : 70,
          "length" : 14
        },
        {
          "activity" : "scanExamplesForR5",
          "start" : 79,
          "length" : 1
        }
      ]
    },
    {
      "name" : "fsh-generated/resources/StructureDefinition-sdo-bundle-resultat-recherche-notification-esms.json",
      "size" : 1127,
      "processes" : [
        {
          "activity" : "loadResources",
          "start" : 31,
          "length" : 10
        },
        {
          "activity" : "load-configure",
          "start" : 32,
          "length" : 1
        },
        {
          "activity" : "load",
          "start" : 32,
          "length" : 5
        },
        {
          "activity" : "generateSnapshots",
          "start" : 32,
          "length" : 102
        },
        {
          "activity" : "generateNarratives",
          "start" : 34,
          "length" : 38
        },
        {
          "activity" : "validate",
          "start" : 37,
          "length" : 384
        },
        {
          "activity" : "generate1",
          "start" : 47,
          "length" : 274
        },
        {
          "activity" : "generate2",
          "start" : 57,
          "length" : 529
        },
        {
          "activity" : "generateValidationPack",
          "start" : 70,
          "length" : 7
        }
      ]
    },
    {
      "name" : "fsh-generated/resources/StructureDefinition-sdo-document-reference.json",
      "size" : 3204,
      "processes" : [
        {
          "activity" : "loadResources",
          "start" : 31,
          "length" : 11
        },
        {
          "activity" : "load",
          "start" : 32,
          "length" : 7
        },
        {
          "activity" : "generateNarratives",
          "start" : 34,
          "length" : 93
        },
        {
          "activity" : "validate",
          "start" : 38,
          "length" : 779
        },
        {
          "activity" : "scanForUsageStats",
          "start" : 44,
          "length" : 1
        },
        {
          "activity" : "generate1",
          "start" : 47,
          "length" : 403
        },
        {
          "activity" : "generate2",
          "start" : 58,
          "length" : 543
        },
        {
          "activity" : "generateValidationPack",
          "start" : 70,
          "length" : 12
        },
        {
          "activity" : "scanExamplesForR5",
          "start" : 79,
          "length" : 1
        }
      ]
    },
    {
      "name" : "fsh-generated/resources/StructureDefinition-sdo-task.json",
      "size" : 18968,
      "processes" : [
        {
          "activity" : "loadResources",
          "start" : 31,
          "length" : 14
        },
        {
          "activity" : "load",
          "start" : 32,
          "length" : 16
        },
        {
          "activity" : "generateSnapshots",
          "start" : 32,
          "length" : 91
        },
        {
          "activity" : "generateNarratives",
          "start" : 34,
          "length" : 149
        },
        {
          "activity" : "validate",
          "start" : 38,
          "length" : 1316
        },
        {
          "activity" : "scanForUsageStats",
          "start" : 44,
          "length" : 2
        },
        {
          "activity" : "generate1",
          "start" : 48,
          "length" : 1220
        },
        {
          "activity" : "generate2",
          "start" : 58,
          "length" : 1047
        },
        {
          "activity" : "generateValidationPack",
          "start" : 70,
          "length" : 33
        },
        {
          "activity" : "scanExamplesForR5",
          "start" : 79,
          "length" : 1
        }
      ]
    },
    {
      "name" : "fsh-generated/resources/Task-exemple-sdo-task.json",
      "size" : 6501,
      "processes" : [
        {
          "activity" : "loadResources",
          "start" : 31,
          "length" : 11
        },
        {
          "activity" : "checkR4R4B",
          "start" : 33,
          "length" : 1
        },
        {
          "activity" : "generateNarratives",
          "start" : 34,
          "length" : 6
        },
        {
          "activity" : "validate",
          "start" : 45,
          "length" : 45
        },
        {
          "activity" : "generate1",
          "start" : 49,
          "length" : 30
        },
        {
          "activity" : "generate2",
          "start" : 59,
          "length" : 9
        }
      ]
    },
    {
      "name" : "fsh-generated/resources/ValueSet-type-document-reference-esms-valueset.json",
      "size" : 781,
      "processes" : [
        {
          "activity" : "loadResources",
          "start" : 31,
          "length" : 13
        },
        {
          "activity" : "load",
          "start" : 32,
          "length" : 3
        },
        {
          "activity" : "generateNarratives",
          "start" : 34,
          "length" : 145
        },
        {
          "activity" : "validate",
          "start" : 35,
          "length" : 123
        },
        {
          "activity" : "generate1",
          "start" : 49,
          "length" : 13
        },
        {
          "activity" : "generate2",
          "start" : 60,
          "length" : 1596
        }
      ]
    }
  ]
}
